pyodoo/__init__.py
pyodoo/active_status_choice.py
pyodoo/boolean_operator.py
pyodoo/compare_type.py
pyodoo/constants.py
pyodoo/filter.py
pyodoo/message_subtype.py
pyodoo/samples/__init__.py
pyodoo/samples/awaitable.py
pyodoo/samples/contacts.py
pyodoo/samples/contacts_async.py
pyodoo/samples/python_code.py
pyodoo/samples/sql_excel_query.py
pyodoo/v12/__init__.py
pyodoo/v12/api.py
pyodoo/v12/model.py
pyodoo/v12/python_code.py
pyodoo/v12/sql_excel_query.py
pyodoo-0.7.2.dist-info/licenses/LICENSE
pyodoo-0.7.2.dist-info/METADATA
pyodoo-0.7.2.dist-info/WHEEL
pyodoo-0.7.2.dist-info/top_level.txt
pyodoo-0.7.2.dist-info/RECORD
