Metadata-Version: 2.4
Name: PyOdoo
Version: 0.7.2
Summary: API for Odoo
Author-email: Fabio Castelli <muflone@muflone.com>
License-Expression: GPL-3.0-or-later
Project-URL: Homepage, http://www.muflone.com/pyodoo/
Project-URL: Source, https://github.com/muflone/pyodoo/
Project-URL: Issues, https://github.com/muflone/pyodoo/issues
Project-URL: Releases, https://github.com/muflone/pyodoo/releases
Classifier: Development Status :: 1 - Planning
Classifier: Intended Audience :: Developers
Classifier: Operating System :: OS Independent
Classifier: Programming Language :: Python :: 3
Classifier: Programming Language :: Python :: 3.10
Classifier: Programming Language :: Python :: 3.11
Classifier: Programming Language :: Python :: 3.12
Classifier: Programming Language :: Python :: 3.13
License-File: LICENSE
Requires-Dist: xlrd~=2.0
Requires-Dist: requests~=2.32
Dynamic: license-file
